dynoxt/utils.py
dynoxt-0.0.1.dist-info/METADATA
dynoxt-0.0.1.dist-info/WHEEL
dynoxt-0.0.1.dist-info/RECORD
